eprime_data/__init__.py
eprime_data/__main__.py
eprime_data/constants.py
eprime_data/dataframe.py
eprime_data/dict_tab_data.py
eprime_data/lib.py
eprime_data-0.2.5.dist-info/entry_points.txt
eprime_data-0.2.5.dist-info/LICENSE
eprime_data-0.2.5.dist-info/WHEEL
eprime_data-0.2.5.dist-info/METADATA
eprime_data-0.2.5.dist-info/RECORD
