Metadata-Version: 2.1
Name: eprime_data
Version: 0.2.5
Summary: Library & command line interface to handle and convert E-Prime log-data (.txt)
Keywords: open science,experimental psychology,data analysis
Author-email: Oliver Lindemann <lindemann@essb.eur.nl>
Requires-Python: >=3.8
Classifier: Programming Language :: Python :: 3
Classifier: Operating System :: OS Independent
Requires-Dist: pandas>=2.1
Requires-Dist: pyarrow>=16.0
Project-URL: Home, https://github.com/lindemann09/eprime-data
